passphrasegen
