Metadata-Version: 1.1
Name: passphrasegen
Version: 1.1
Summary: Generate a passphrase consisting of words chosen from word list dictionaries.
Home-page: https://github.com/rpatterson/passphrasegen
Author: Ross Patterson
Author-email: me@rpatterson.net
License: GPLv2
Keywords: password generator passphrase entropy
Platform: UNKNOWN
Classifier: Development Status :: 4 - Beta
Classifier: Environment :: Console
Classifier: Intended Audience :: End Users/Desktop
Classifier: License :: OSI Approved :: GNU General Public License v2 (GPLv2)
Classifier: Natural Language :: English
Classifier: Programming Language :: Python
Classifier: Topic :: Security
Classifier: Topic :: Utilities
